runvenv/__init__.py
runvenv/__main__.py
runvenv-0.5.1.dist-info/licenses/LICENSE
runvenv-0.5.1.dist-info/METADATA
runvenv-0.5.1.dist-info/WHEEL
runvenv-0.5.1.dist-info/entry_points.txt
runvenv-0.5.1.dist-info/top_level.txt
runvenv-0.5.1.dist-info/RECORD
