Metadata-Version: 2.4
Name: runvenv
Version: 0.5.1
Summary: run python scripts or modules in a venv with a single command
Author-email: Philipp Unger <philipp.unger.1988@gmail.com>
License-Expression: MIT
Project-URL: Homepage, https://github.com/philippun1/runvenv
Project-URL: Repository, https://github.com/philippun1/runvenv
Project-URL: Bug Tracker, https://github.com/philippun1/runvenv/issues
Classifier: Programming Language :: Python :: 3.8
Classifier: Programming Language :: Python :: 3.9
Classifier: Programming Language :: Python :: 3.10
Classifier: Programming Language :: Python :: 3.11
Classifier: Programming Language :: Python :: 3.12
Classifier: Programming Language :: Python :: 3.13
Classifier: Programming Language :: Python :: 3.14
Requires-Python: >=3.8
License-File: LICENSE
Dynamic: license-file
